_quickfix.cpython-39-darwin.so
quickfix.py
quickfix40.py
quickfix41.py
quickfix42.py
quickfix43.py
quickfix44.py
quickfix50.py
quickfix50sp1.py
quickfix50sp2.py
quickfixt11.py
quickfix_M1-1.15.1.data/data/share/quickfix/FIX40.xml
quickfix_M1-1.15.1.data/data/share/quickfix/FIX41.xml
quickfix_M1-1.15.1.data/data/share/quickfix/FIX42.xml
quickfix_M1-1.15.1.data/data/share/quickfix/FIX43.xml
quickfix_M1-1.15.1.data/data/share/quickfix/FIX44.xml
quickfix_M1-1.15.1.data/data/share/quickfix/FIX50.xml
quickfix_M1-1.15.1.data/data/share/quickfix/FIX50SP1.xml
quickfix_M1-1.15.1.data/data/share/quickfix/FIX50SP2.xml
quickfix_M1-1.15.1.data/data/share/quickfix/FIXT11.xml
quickfix_M1-1.15.1.dist-info/LICENSE
quickfix_M1-1.15.1.dist-info/METADATA
quickfix_M1-1.15.1.dist-info/WHEEL
quickfix_M1-1.15.1.dist-info/top_level.txt
quickfix_M1-1.15.1.dist-info/RECORD
