Metadata-Version: 2.1
Name: quickfix-M1
Version: 1.15.1
Summary: FIX (Financial Information eXchange) protocol implementation
Home-page: http://www.quickfixengine.org
Download-URL: http://www.quickfixengine.org
Author: Oren Miller
Author-email: oren@quickfixengine.org
Maintainer: Oren Miller
Maintainer-email: oren@quickfixengine.org
License: The QuickFIX Software License, Version 1.0
License-File: LICENSE
